.coveragerc
.env
.testr.conf
AUTHORS
ChangeLog
Procfile
README.rst
config.yml
init_kit.sh
install.sh
install.txt
manage.py
readme_zh.rst
requirement-conda.txt
requirements.in
requirements.txt
requirements.txt_bak
setup.cfg
setup.py
tasks.py
temp.txt
template_test.pytemplate
test-requirements.in
test-requirements.txt
tox.ini
backup/databank/applications.bson
backup/databank/applications.metadata.json
backup/databank/fs.chunks.bson
backup/databank/fs.chunks.metadata.json
backup/databank/posts.bson
backup/databank/posts.metadata.json
backup/databank/settings.bson
backup/databank/settings.metadata.json
backup/databank/system.indexes.bson
backup/databank/users.bson
backup/databank/users.metadata.json
backup/redis/appendonly.aof
backup/redis/redis/appendonly.aof
bin/.Rhistory
bin/add
bin/addchk
bin/babelunix
bin/batsub
bin/calc.sh
bin/client
bin/cnum
bin/collectf
bin/collectf2
bin/collectff
bin/da.sh
bin/del_all_qtask
bin/dmv
bin/energy-cut
bin/err-txt
bin/fake90
bin/findhf
bin/findhf.py
bin/findhf2
bin/findhf22
bin/findhf2_collect
bin/findhf3
bin/findhf4
bin/findhf_new
bin/findimag
bin/findkey
bin/gb
bin/generate
bin/getbinpath
bin/getxyz
bin/gm
bin/hftest
bin/killmain
bin/labgxrun
bin/labkit
bin/labsub
bin/labsub_lab
bin/labsub_super
bin/linesort
bin/lld
bin/load_config.rb
bin/lsd
bin/m.nodekill
bin/mchangename
bin/mdemo
bin/merge
bin/metacalc
bin/metacalc_err
bin/metacalc_txt
bin/mfreqchk
bin/mfreqinfo
bin/mjoin
bin/mmv
bin/mout-freq
bin/mout-txt
bin/mout-xyz
bin/moutinfo
bin/mrecompute
bin/mrename
bin/mresort
bin/mtxt-xyz
bin/mv_low
bin/mv_nimag
bin/mxyz-txt
bin/mykill
bin/mytest
bin/next
bin/node.gen
bin/nodekill
bin/out-txt
bin/out-xyz
bin/out2txt
bin/out2xyz
bin/outinfo
bin/overtime_hfopt
bin/overtime_pm3
bin/pdb-out
bin/pdb-out.py
bin/pid_tree.py
bin/pscpu
bin/pscpu-node
bin/pscpuall-single
bin/psusr
bin/psusr91
bin/qdel_byqname
bin/recompute
bin/record
bin/rename_xlsx.py
bin/run
bin/serv
bin/task.gtmp
bin/tempeture_distribution.R
bin/tmux
bin/txt-xyz
bin/wlt.py
labkit.egg-info/PKG-INFO
labkit.egg-info/SOURCES.txt
labkit.egg-info/dependency_links.txt
labkit.egg-info/entry_points.txt
labkit.egg-info/not-zip-safe
labkit.egg-info/pbr.json
labkit.egg-info/requires.txt
labkit.egg-info/top_level.txt
