Metadata-Version: 1.1
Name: labkit
Version: 0.0.3.dev11
Summary: commutils
Home-page: https://github.com/lhrkkk/labkit.git
Author: lhr
Author-email: airhenry@gmail.com
License: UNKNOWN
Platform: UNKNOWN
Classifier: Environment :: Console
Classifier: Intended Audience :: Developers
Classifier: Intended Audience :: Education
Classifier: License :: OSI Approved :: GNU General Public License v2 (GPLv2)
Classifier: Operating System :: POSIX :: Linux
Classifier: Programming Language :: Python
Classifier: Programming Language :: Python :: 2
Classifier: Programming Language :: Python :: 2.7
